doc2vec2cluster/__init__.py
doc2vec2cluster/_nbdev.py
doc2vec2cluster/core.py
doc2vec2cluster/kmeans.py
doc2vec2cluster/nearest.py
doc2vec2cluster-0.0.1.dist-info/LICENSE
doc2vec2cluster-0.0.1.dist-info/LICENSE.md
doc2vec2cluster-0.0.1.dist-info/METADATA
doc2vec2cluster-0.0.1.dist-info/WHEEL
doc2vec2cluster-0.0.1.dist-info/entry_points.txt
doc2vec2cluster-0.0.1.dist-info/top_level.txt
doc2vec2cluster-0.0.1.dist-info/RECORD
