Metadata-Version: 2.1
Name: doc2vec2cluster
Version: 0.0.1
Summary: Cluster the documents using doc2vec
Home-page: https://github.com/JiaxiangBU/doc2vec2cluster
Author: Jiaxiang Li
Author-email: alex.lijiaxiang@foxmail.com
License: Apache Software License 2.0
Keywords: word2vec cluster
Platform: UNKNOWN
Classifier: Development Status :: 3 - Alpha
Classifier: Intended Audience :: Developers
Classifier: License :: OSI Approved :: Apache Software License
Classifier: Natural Language :: English
Classifier: Programming Language :: Python :: 3.6
Classifier: Programming Language :: Python :: 3.7
Classifier: Programming Language :: Python :: 3.8
Requires-Python: >=3.6
